[
	[
		{
			"rt":{"x":0, "y":0}, "lt":{"x":0, "y":0},"rb":{"x":0, "y":0},"lb":{"x":0, "y":0}
		},
		{
			"rt":{"x":0, "y":0}, "lt":{"x":0, "y":0},"rb":{"x":0, "y":-0.1},"lb":{"x":0, "y":-0.1}
		},
		{
			"rt":{"x":0, "y":0}, "lt":{"x":0, "y":0},"rb":{"x":0, "y":0},"lb":{"x":0, "y":0}
		}
	],
	[
		{
			"rt":{"x":0, "y":0}, "lt":{"x":0, "y":0},"rb":{"x":0, "y":0},"lb":{"x":0, "y":0}
		},
		{
			"rt":{"x":0, "y":0}, "lt":{"x":0, "y":0},"rb":{"x":0, "y":0},"lb":{"x":0, "y":0}
		},
		{
			"rt":{"x":0, "y":0}, "lt":{"x":0, "y":0},"rb":{"x":-0.5, "y":0},"lb":{"x":0.2, "y":0}
		}
	],
	[
		{
			"rt":{"x":0, "y":0}, "lt":{"x":0, "y":0},"rb":{"x":0, "y":0},"lb":{"x":0, "y":0}
		},
		{
			"rt":{"x":0, "y":0}, "lt":{"x":0, "y":0},"rb":{"x":-0.5, "y":0},"lb":{"x":-0.25, "y":0}
		},
		{
			"rt":{"x":0, "y":0}, "lt":{"x":0, "y":0},"rb":{"x":0, "y":0},"lb":{"x":0, "y":0}
		}
	]
]
